{"Month":9,"Year":2025,"DaysData":[{"Date":"2025/09/01","Type":"poem","Title":null,"Link":"poems/01.09.25.html"},{"Date":"2025/09/02","Type":"poem","Title":null,"Link":"poems/02.09.25.html"},{"Date":"2025/09/03","Type":"poem","Title":null,"Link":"poems/03.09.25.html"},{"Date":"2025/09/04","Type":"poem","Title":null,"Link":"poems/04.09.25.html"},{"Date":"2025/09/05","Type":"poem","Title":null,"Link":"poems/05.09.25.html"},{"Date":"2025/09/06","Type":"poem","Title":null,"Link":"poems/06.09.25.html"},{"Date":"2025/09/07","Type":"poem","Title":null,"Link":"poems/07.09.25.html"},{"Date":"2025/09/08","Type":"poem","Title":null,"Link":"poems/08.09.25.html"},{"Date":"2025/09/09","Type":"poem","Title":null,"Link":"poems/09.09.25.html"},{"Date":"2025/09/10","Type":"poem","Title":null,"Link":"poems/10.09.25.html"},{"Date":"2025/09/11","Type":"poem","Title":null,"Link":"poems/11.09.25.html"},{"Date":"2025/09/12","Type":"poem","Title":null,"Link":"poems/12.09.25.html"},{"Date":"2025/09/13","Type":"poem","Title":null,"Link":"poems/13.09.25.html"},{"Date":"2025/09/14","Type":"poem","Title":null,"Link":"poems/14.09.25.html"},{"Date":"2025/09/15","Type":"poem","Title":null,"Link":"poems/15.09.25.html"},{"Date":"2025/09/16","Type":"poem","Title":null,"Link":"poems/16.09.25.html"},{"Date":"2025/09/17","Type":"poem","Title":null,"Link":"poems/17.09.25.html"},{"Date":"2025/09/18","Type":"poem","Title":null,"Link":"poems/18.09.25.html"},{"Date":"2025/09/19","Type":"poem","Title":null,"Link":"poems/19.09.25.html"},{"Date":"2025/09/20","Type":"poem","Title":null,"Link":"poems/20.09.25.html"},{"Date":"2025/09/21","Type":"poem","Title":null,"Link":"poems/21.09.25.html"},{"Date":"2025/09/22","Type":"poem","Title":null,"Link":"poems/22.09.25.html"},{"Date":"2025/09/23","Type":"poem","Title":null,"Link":"poems/23.09.25.html"},{"Date":"2025/09/24","Type":"poem","Title":null,"Link":"poems/24.09.25.html"},{"Date":"2025/09/25","Type":"poem","Title":null,"Link":"poems/25.09.25.html"},{"Date":"2025/09/26","Type":"poem","Title":null,"Link":"poems/26.09.25.html"},{"Date":"2025/09/27","Type":"poem","Title":null,"Link":"poems/27.09.25.html"},{"Date":"2025/09/28","Type":"poem","Title":null,"Link":"poems/28.09.25.html"},{"Date":"2025/09/29","Type":"poem","Title":null,"Link":"poems/29.09.25.html"},{"Date":"2025/09/30","Type":"poem","Title":null,"Link":"poems/30.09.25.html"}],"MinYear":2004}